torchsvm/__init__.py
torchsvm/cvkall3.py
torchsvm/cvkdwd.py
torchsvm/cvkhuber.py
torchsvm/cvklogit.py
torchsvm/cvknyssvm.py
torchsvm/cvksqsvm.py
torchsvm/cvksvm.py
torchsvm/functions.py
torchsvm/kernels.py
torchsvm/platt.py
torchsvm-3.0.2.dist-info/licenses/LICENSE
torchsvm-3.0.2.dist-info/METADATA
torchsvm-3.0.2.dist-info/WHEEL
torchsvm-3.0.2.dist-info/top_level.txt
torchsvm-3.0.2.dist-info/RECORD
