Metadata-Version: 2.4
Name: torchsvm
Version: 3.0.2
Summary: torchsvm, a PyTorch-based library that trains kernel SVMs and other large-margin classifiers 
Home-page: https://github.com/YikaiZhang95/torchsvm
Author: Yikai Zhang
Author-email: yikai-zhang@uiowa.edu
License: MIT
Classifier: Programming Language :: Python :: 3
Classifier: License :: OSI Approved :: MIT License
Classifier: Operating System :: OS Independent
Requires-Python: >=3.7
License-File: LICENSE
Requires-Dist: numpy==1.25.2
Requires-Dist: pandas==1.5.2
Requires-Dist: pytest==8.3.4
Requires-Dist: scikit-learn==1.1.3
Requires-Dist: scipy==1.9.3
Requires-Dist: seaborn==0.12.1
Requires-Dist: torch==2.4.1
Provides-Extra: dev
Requires-Dist: pytest; extra == "dev"
Requires-Dist: black; extra == "dev"
Requires-Dist: flake8; extra == "dev"
Dynamic: author
Dynamic: classifier
Dynamic: description
Dynamic: description-content-type
Dynamic: home-page
Dynamic: license
Dynamic: license-file
Dynamic: requires-dist
Dynamic: summary
